octoprint_fixcbdfirmware/__init__.py
OctoPrint_FixCBDFirmware-0.4.0.dist-info/LICENSE
OctoPrint_FixCBDFirmware-0.4.0.dist-info/METADATA
OctoPrint_FixCBDFirmware-0.4.0.dist-info/WHEEL
OctoPrint_FixCBDFirmware-0.4.0.dist-info/entry_points.txt
OctoPrint_FixCBDFirmware-0.4.0.dist-info/top_level.txt
OctoPrint_FixCBDFirmware-0.4.0.dist-info/RECORD
