Metadata-Version: 2.1
Name: OctoPrint-FixCBDFirmware
Version: 0.4.0
Summary: Fixes communication with a broken firmware making its rounds that identifies as 'CBD make it'
Home-page: https://github.com/OctoPrint/OctoPrint-FixCBDFirmware
Author: Gina Häußge
Author-email: gina@octoprint.org
License: AGPLv3
Platform: UNKNOWN
Requires-Dist: OctoPrint
Provides-Extra: develop
Requires-Dist: pre-commit ; extra == 'develop'
